torchfree_ocr/__init__.py
torchfree_ocr/cli.py
torchfree_ocr/config.py
torchfree_ocr/craft_utils.py
torchfree_ocr/detection.py
torchfree_ocr/imgproc.py
torchfree_ocr/recognition.py
torchfree_ocr/torchfree_ocr.py
torchfree_ocr/utils.py
torchfree_ocr-1.1.0.dist-info/LICENSE.txt
torchfree_ocr-1.1.0.dist-info/METADATA
torchfree_ocr-1.1.0.dist-info/WHEEL
torchfree_ocr-1.1.0.dist-info/entry_points.txt
torchfree_ocr-1.1.0.dist-info/top_level.txt
torchfree_ocr-1.1.0.dist-info/RECORD
