Metadata-Version: 2.1
Name: torchfree-ocr
Version: 1.1.0
Summary: EasyOCR without pytorch
Home-page: https://github.com/SeldonHZ/torchfree-ocr-en
Download-URL: https://github.com/SeldonHZ/torchfree-ocr-en.git
License: Apache License 2.0
Keywords: ocr optical character recognition deep learning neural network
License-File: LICENSE.txt
Requires-Dist: opencv-python-headless
Requires-Dist: numpy
Requires-Dist: onnxruntime
Requires-Dist: Pillow
Requires-Dist: python-bidi
